{
  "name": "Ordonnance",
  "plural": "Ordonnances",
  "base": "PersistedModel",
  "idInjection": true,
  "options": {
    "validateUpsert": true
  },
  "properties": {
    "speciality": {
      "type": "string",
      "required": true
    },
    "pathology": {
      "type": "string",
      "required": true
    },
    "clinicalPresentation": {
      "type": "string",
      "required": true
    },
    "Recommandation": {
      "type": "string",
      "required": true
    }
  },
  "validations": [],
  "relations": {
    "molecules": {
      "type": "hasMany",
      "model": "Molecule",
      "foreignKey": "ordonnanceId"
    }
  },
  "acls": [],
  "methods": {}
}
